{"data":{"site":{"siteMetadata":{"title":"My Fretboard"}},"allChordsJson":{"edges":[{"node":{"id":"a-sharp-major","placements":[0,3,3,3,0,null],"fingerings":[0,4,3,2,0,0],"bar":{"start":1,"end":5,"fret":1},"variations":null}},{"node":{"id":"a-major","placements":[0,2,2,2,0,null],"fingerings":[0,2,1,3,0,0],"bar":null,"variations":[{"placements":[0,5,2,null,3,0],"fingerings":[0,4,1,0,3,0]},{"placements":[5,null,null,7,4,0],"fingerings":[2,0,0,4,1,0]}]}},{"node":{"id":"b-major","placements":[0,4,4,4,0,null],"fingerings":[0,4,3,2,0,0],"bar":{"start":1,"end":5,"fret":2},"variations":null}},{"node":{"id":"c-major","placements":[0,1,0,2,3,null],"fingerings":[0,1,0,2,3,0],"bar":null,"variations":[{"placements":[0,5,5,5,0,0],"fingerings":[0,4,3,2,0,0]}]}},{"node":{"id":"c-sharp-major","placements":[0,6,6,6,0,0],"fingerings":[0,4,3,2,0,0],"bar":{"start":1,"end":6,"fret":4},"variations":null}},{"node":{"id":"d-major","placements":[2,3,2,0,null,null],"fingerings":[2,3,1,0,0,0],"bar":null,"variations":null}},{"node":{"id":"e-major","placements":[0,0,1,2,2,0],"fingerings":[0,0,1,3,2,0],"bar":null,"variations":null}},{"node":{"id":"f-major","placements":[0,0,2,3,3,0],"fingerings":[0,0,2,4,3,0],"bar":{"start":1,"end":6,"fret":1},"variations":null}},{"node":{"id":"g-major","placements":[3,3,0,0,2,3],"fingerings":[4,3,0,0,1,2],"bar":null,"variations":null}}]}}}